rc_orchestration_sdk/__init__.py
rc_orchestration_sdk/client.py
rc_orchestration_sdk/client_async.py
rc_orchestration_sdk/client_sync.py
rc_orchestration_sdk/exceptions.py
rc_orchestration_sdk/models.py
rc_orchestration_sdk/py.typed
rc_orchestration_sdk-1.1.1.dist-info/METADATA
rc_orchestration_sdk-1.1.1.dist-info/WHEEL
rc_orchestration_sdk-1.1.1.dist-info/top_level.txt
rc_orchestration_sdk-1.1.1.dist-info/RECORD
