Metadata-Version: 2.4
Name: rc-orchestration-sdk
Version: 1.1.1
Summary: Production-quality Python SDK for FounderX-AI Orchestration API with sync/async support, automatic retries, and comprehensive error handling
Author-email: FounderX-AI <dev@founder-x.ai>
Maintainer-email: FounderX-AI <dev@founder-x.ai>
License-Expression: MIT
Project-URL: Homepage, https://github.com/founderx-ai/RooCommands
Project-URL: Documentation, https://docs.founder-x.ai/sdk/python
Project-URL: Repository, https://github.com/founderx-ai/RooCommands
Project-URL: Issues, https://github.com/founderx-ai/RooCommands/issues
Project-URL: Changelog, https://github.com/founderx-ai/RooCommands/blob/main/orchestration-system/sdk/python/CHANGELOG.md
Keywords: orchestration,api,sdk,founderx,automation,workflow,llm,ai,founderx-ai
Classifier: Development Status :: 5 - Production/Stable
Classifier: Intended Audience :: Developers
Classifier: Programming Language :: Python :: 3
Classifier: Programming Language :: Python :: 3.9
Classifier: Programming Language :: Python :: 3.10
Classifier: Programming Language :: Python :: 3.11
Classifier: Programming Language :: Python :: 3.12
Classifier: Programming Language :: Python :: 3.13
Classifier: Topic :: Software Development :: Libraries :: Python Modules
Classifier: Topic :: Internet :: WWW/HTTP
Classifier: Typing :: Typed
Requires-Python: >=3.9
Requires-Dist: requests>=2.31.0
Requires-Dist: httpx>=0.25.0
Requires-Dist: pydantic>=2.0.0
Provides-Extra: dev
Requires-Dist: pytest>=7.0.0; extra == "dev"
Requires-Dist: pytest-asyncio>=0.21.0; extra == "dev"
Requires-Dist: pytest-cov>=4.0.0; extra == "dev"
Requires-Dist: black>=23.0.0; extra == "dev"
Requires-Dist: mypy>=1.0.0; extra == "dev"
Requires-Dist: ruff>=0.1.0; extra == "dev"
